{"src": ["腾讯娱乐", "
"], "title": ["《杀破狼2》试映口碑爆棚 吴京再获观众点赞"], "url": ["http://ent.qq.com/a/20150607/009293.htm"], "pdate": ["2015-06-07 10:50:56"], "image": ["http://img1.gtimg.com/ent/pics/hv1/166/189/1855/120669736_small.jpg"], "content": ["《杀破狼2》明星见面会吴京与数千名观众见面《杀破狼2》试映会场面火爆非常吴京受热捧《杀破狼2》颜值最高动作威猛观众大呼过瘾吴京“动作高考”获观众高分点赞腾讯娱乐讯2015暑期档华...", "
"]}
{"src": ["腾讯娱乐", "
"], "title": ["李易峰新片开机 多部作品定档再迎“峰收”季"], "url": ["http://ent.qq.com/a/20150607/008442.htm"], "pdate": ["2015-06-07 10:05:35"], "image": ["http://img1.gtimg.com/ent/pics/hv1/101/182/1855/120667886_small.jpg"], "content": ["日前，当红人气偶像李易峰在微博晒出一张上海外滩图片，同时隔空对话好友杨幂，暗示两人或将再次合作，消息一出便引起广大粉丝争相猜测。...", "
"]}
{"src": ["腾讯娱乐", "
"], "title": ["《商学院合伙人》唐嫣金圣柱演情侣甜蜜互动"], "url": ["http://ent.qq.com/a/20150606/013866.htm"], "pdate": ["2015-06-06 12:44:06"], "image": ["http://img1.gtimg.com/ent/pics/hv1/218/130/1855/120654743_small.jpg"], "content": ["唐嫣金圣柱合影腾讯娱乐讯6月4日，亚洲偶像男团UNIQ的成员金圣柱开通微博，首条微博即艾特了唐嫣并晒出两人的亲密合影，透露自己加盟出演了电影《商学院合伙人》，唐嫣随即转发，亲昵的...", "
"]}
{"src": ["腾讯娱乐", "
"], "title": ["电影《顺风车》公映引热议：低碳环保正能量"], "url": ["http://ent.qq.com/a/20150606/013852.htm"], "pdate": ["2015-06-06 12:42:32"], "image": ["http://img1.gtimg.com/ent/pics/hv1/202/130/1855/120654727_small.jpg"], "content": ["顺风车发起人王永腾讯娱乐讯由李广德、岳晓琳联合执导，王永、张会中领衔主演，周晓鸥、邵峰等倾情出演的国内首部关注交通问题的公益喜剧电影《顺风车》已于6月5日在全国上映。该片一经上映...", "
"]}
{"src": ["腾讯娱乐", "
"], "title": ["《怦然星动》开机 杨幂李易峰“九百年”后续缘"], "url": ["http://ent.qq.com/a/20150606/009424.htm"], "pdate": ["2015-06-06 09:28:59"], "image": ["http://img1.gtimg.com/12/1279/127966/12796609_small.jpg"], "content": ["腾讯娱乐讯 6月5日，由陈国辉执导，杨幂、李易峰领衔主演的浪漫爱情喜剧《怦然星动》在上海正式开机。这对“网络最具人气组合”继《古剑奇谭》之后终于再度合体。当天上午，杨幂和李易峰便...", "
"]}
{"src": ["腾讯娱乐", "
"], "title": ["《横冲直撞好莱坞》发MV 钟汉良唱《普通人》"], "url": ["http://ent.qq.com/a/20150606/009324.htm"], "pdate": ["2015-06-06 09:21:48"], "image": ["http://img1.gtimg.com/ent/pics/hv1/115/112/1855/120650050_small.jpg"], "content": ["钟汉良录音花絮腾讯娱乐讯《速度与激情》系列导演林诣彬监制并编剧，赵薇、黄晓明、佟大为联合主演的好莱坞式喜剧大片《横冲直撞好莱坞》即将于6月26日爆笑上映。今日，片方发布一支20秒...", "
"]}
{"src": ["腾讯娱乐", "
"], "title": ["周末分级指导 末日崩塌、顺风车适合7岁以上"], "url": ["http://ent.qq.com/a/20150606/006614.htm"], "pdate": ["2015-06-06 07:35:40"], "image": ["http://img1.gtimg.com/ent/pics/hv1/150/105/1855/120648300_small.png"], "content": ["三部国产片“围攻”《末日崩塌》。其中《顺风车》适合7岁以上观众，《搏击迷城》因为部分设定较为黑暗，同时牵涉到暴力镜头，适合13岁以上观众。《异种》有怪兽和血腥镜头，适合16岁以上...", "
"]}
{"src": ["腾讯娱乐", "
"], "title": ["在中国大剧院留印怎么就成国际玩笑了？"], "url": ["http://ent.qq.com/a/20150606/005657.htm"], "pdate": ["2015-06-06 07:20:28"], "image": ["http://img1.gtimg.com/ent/pics/hv1/140/98/1855/120646505_small.jpg"], "content": ["林诣彬、赵薇、黄晓明好莱坞留印腾讯娱乐专稿文/真真策划、编辑/小猱洛杉矶当地时间6月3日上午，《横冲直撞好莱坞》主演赵薇、黄晓明，监制林诣彬在好莱坞中国剧院前留下了手印、脚印。活...", "
"]}
{"src": ["腾讯娱乐", "
"], "title": ["旅游卫视《行者》推纪录片 聚焦儿童教育话题"], "url": ["http://ent.qq.com/a/20150605/043509.htm"], "pdate": ["2015-06-05 16:11:26"], "image": ["http://img1.gtimg.com/ent/pics/hv1/158/41/1855/120631988_small.jpg"], "content": ["活动现场腾讯娱乐讯（文/三三视频/秦付强）北京时间6月4日，由旅游卫视《行者》节目耗时7个月参与拍摄制作的15集户外纪录片《别叫我宝贝》，在卢米埃北京芳草地影城举行媒体见面暨首映...", "
"]}
{"src": ["腾讯娱乐", "
"], "title": ["《致青春2》高考加油海报 吴亦凡刘亦菲美好出镜"], "url": ["http://ent.qq.com/a/20150605/040386.htm"], "pdate": ["2015-06-05 15:14:54"], "image": ["http://img1.gtimg.com/12/1279/127924/12792454_small.jpg"], "content": ["腾讯娱乐讯 6月5日，距离牵动无数人心的全国高考还有两天。当天，纯爱电影《致青春2：原来你还在这里》片方倾情发布了一组风格清新的“高考加油”版海报，与海报同步推出的还有主创们专门...", "
"]}
{"src": ["腾讯娱乐", "
"], "title": ["《末日崩塌》稳坐票房榜首 被赞“全程无尿点”"], "url": ["http://ent.qq.com/a/20150605/036557.htm"], "pdate": ["2015-06-05 14:09:34"], "image": ["http://img1.gtimg.com/12/1279/127913/12791368_small.jpg"], "content": ["腾讯娱乐讯 由华纳兄弟影业出品的2015年度灾难巨制《末日崩塌》已于6月2日在全国上映，仅3天便收获超高票房，稳坐票房榜首。影片从演员挑选、特效制作到剧情设置均获得一片好评，赞扬...", "
"]}
{"src": ["腾讯娱乐", "
"], "title": ["《侏罗纪世界》曝终极预告 6月10日震撼来袭"], "url": ["http://ent.qq.com/a/20150605/034279.htm"], "pdate": ["2015-06-05 13:56:34"], "image": ["http://img1.gtimg.com/12/1279/127911/12791181_small.jpg"], "content": ["腾讯娱乐讯 由环球影业出品，史蒂文·斯皮尔伯格监制的好莱坞巨制《侏罗纪世界》今日曝光了终极预告片。预告片中，具有超高智商的暴虐霸王龙挣脱了人类的控制，“血洗侏罗纪世界主题公园”。...", "
"]}
{"src": ["腾讯娱乐", "
"], "title": ["80后电影人张珈铭：别具一格的影视产业布局"], "url": ["http://ent.qq.com/a/20150605/033805.htm"], "pdate": ["2015-06-05 13:36:09"], "image": ["http://img1.gtimg.com/12/1279/127910/12791051_small.jpg"], "content": ["腾讯娱乐讯 “深圳制造”近两年异常活跃，而最近备受关注的便是亮相本届戛纳红毯的80后电影人张珈铭,由他创立并任总裁的金蔷薇影视投资集团所覆盖的业务从影视投资、制作到电影宣传、发行...", "
"]}
{"src": ["腾讯娱乐", "
"], "title": ["《鹦哥岭，最后一枪》开机 康宁开启丛林冒险"], "url": ["http://ent.qq.com/a/20150605/033751.htm"], "pdate": ["2015-06-05 13:33:12"], "image": ["http://img1.gtimg.com/12/1279/127910/12791046_small.jpg"], "content": ["腾讯娱乐讯 日前，被列为海南省重点文化项目的电影《鹦哥岭，最后一枪》在海口举行了开机仪式。当天，除导演金也以及主创人员悉数亮相外，海南省委常委、宣传部长许俊，海南省文体厅、海南省...", "
"]}
{"src": ["腾讯娱乐", "
"], "title": ["《少女哪吒》再曝花絮：化学老师被砸16次"], "url": ["http://ent.qq.com/a/20150605/033732.htm"], "pdate": ["2015-06-05 13:32:00"], "image": ["http://img1.gtimg.com/ent/pics/hv1/192/7/1855/120623352_small.jpg"], "content": ["化学老师被打化学老师被打倒在地化学老师花样被打严厉的化学老师腾讯娱乐讯上课而已，化学老师竟被打16次！怎么会发生这种人（you）神（xie）共（qi）愤（dai）的事情！因为，电...", "
"]}
{"src": ["腾讯娱乐", "
"], "title": ["《大轰炸》演员首聚 车永莉宋承宪卖萌剪刀手"], "url": ["http://ent.qq.com/a/20150605/033583.htm"], "pdate": ["2015-06-05 13:25:10"], "image": ["http://img1.gtimg.com/ent/pics/hv1/0/7/1855/120623160_small.jpg"], "content": ["《大轰炸》剧组首次相聚车永莉陈伟霆车永莉宋承宪腾讯娱乐讯由著名导演萧锋执导、采用全线奥斯卡获奖班底制作、好莱坞及两岸三地的众多大牌明星联袂出演的电影《大轰炸》正在如火如荼得拍摄中...", "
"]}
{"src": ["腾讯娱乐", "
"], "title": ["《我是谁2015》姚星彤、张蓝心绝色双杀"], "url": ["http://ent.qq.com/a/20150605/033529.htm"], "pdate": ["2015-06-05 13:22:09"], "image": ["http://img1.gtimg.com/12/1279/127909/12790998_small.jpg"], "content": ["腾讯娱乐讯 由成龙监制的动作喜剧电影《我是谁2015》即将于6月12日杀上银幕。影片由新生代导演宋胤熹执导，成家班精锐班底倾力加盟。在《十二生肖》中双杀亮相的姚星彤、张蓝心在这部...", "
"]}
{"src": ["腾讯娱乐", "
"], "title": ["《异种》今日公映 曝正面海报恶兽真面目曝光"], "url": ["http://ent.qq.com/a/20150605/033474.htm"], "pdate": ["2015-06-05 13:19:40"], "image": ["http://img1.gtimg.com/12/1279/127909/12790984_small.jpg"], "content": ["  腾讯娱乐讯 重口味新型惊悚电影《异种》于今日开始全国公映，片方发布“正面全裸”版海报，将机械生物特效技术和CG特效技术打造的银幕特效怪兽的真正面目公之于众，而首次将变异怪兽元...", "
"]}
{"src": ["腾讯娱乐", "
"], "title": ["张智皓《太极侠》 搭档基努李维斯演保镖"], "url": ["http://ent.qq.com/a/20150605/033435.htm"], "pdate": ["2015-06-05 13:16:26"], "image": ["http://img1.gtimg.com/ent/pics/hv1/101/6/1855/120623006_small.jpg"], "content": ["张智皓腾讯娱乐讯近日，一直以功夫片见长，以硬汉形象出现在各类影视剧中的演员张智皓现身某电影发布会现场，此次发布会他并非作为演员出席，而是作为友人站台支持捧场，被问及近况他表示正在...", "
"]}
{"src": ["腾讯娱乐", "
"], "title": ["电影《顺风车》今日公映 揭秘四大看点"], "url": ["http://ent.qq.com/a/20150605/031939.htm"], "pdate": ["2015-06-05 13:05:39"], "image": ["http://img1.gtimg.com/ent/pics/hv1/155/5/1855/120622805_small.jpg"], "content": ["腾讯娱乐讯由王永、张会中主演，周晓鸥、邵峰鼎力加盟的都市轻喜剧《顺风车》于今日（5日）正式登陆全国各大院线。该片主要讲述了某文化公司老板“大奔哥”（王永饰）在堵车时看到路人挤不上...", "
"]}
{"src": ["腾讯娱乐", "
"], "title": ["《恋爱排班表》四角恋剧照 渣男踏两船爱情告急"], "url": ["http://ent.qq.com/a/20150603/039459.htm"], "pdate": ["2015-06-03 14:19:04"], "image": ["http://img1.gtimg.com/12/1277/127704/12770498_small.jpg"], "content": ["  腾讯娱乐讯 爱情喜剧电影《恋爱排班表》曝光了一组最新的“四角关系”剧照，许晴、车晓、华少以及陈武康四位主演悉数亮相。从剧照看来，渣男周旋于两个女人之间，把爱情中温馨居家与文艺...", "
"]}
{"src": ["腾讯娱乐", "
"], "title": ["《杀破狼2》硬汉柔情 托尼贾护女暴揍吴京张晋"], "url": ["http://ent.qq.com/a/20150603/039286.htm"], "pdate": ["2015-06-03 14:15:44"], "image": ["http://img1.gtimg.com/12/1277/127704/12770479_small.jpg"], "content": ["  腾讯娱乐讯 由博纳影业、太阳娱乐、银都机构等联合出品的最强3D动作电影《杀破狼2》将于6月18日公映。影片汇集了吴京、张晋、托尼贾、古天乐、任达华、张驰等亚洲影坛实力阵容，打...", "
"]}
{"src": ["腾讯娱乐", "
"], "title": ["《杀破狼2》最强动作IP 吴京张晋续写传奇"], "url": ["http://ent.qq.com/a/20150605/031442.htm"], "pdate": ["2015-06-05 13:04:18"], "image": ["http://img1.gtimg.com/12/1279/127909/12790927_small.jpg"], "content": ["  腾讯娱乐讯 由博纳影业、太阳娱乐、银都机构等联合出品的终极3D动作电影《杀破狼2》，十年后再度重启“拳”力出击，已定档6月18日今夏再度掀起动作狂潮。十年前《杀破狼》斩获了香...", "
"]}
{"src": ["腾讯娱乐", "
"], "title": ["电影《济公》拍摄正酣 中韩明星火花大碰撞"], "url": ["http://ent.qq.com/a/20150605/031404.htm"], "pdate": ["2015-06-05 13:01:04"], "image": ["http://img1.gtimg.com/ent/pics/hv1/77/5/1855/120622727_small.jpg"], "content": ["安七炫童菲郑元畅腾讯娱乐讯近日，由杭州南广影视投资，著名导演刘嘉靖执导的传奇古装喜剧电影《济公》正在横店影视城火热拍摄中。该片自开拍之日起就赢得了各路媒体关注，尤其是两岸四地大批...", "
"]}
{"src": ["腾讯娱乐", "
"], "title": ["《我是奋青》曝剧照 孙坚帅萌有型毛晓彤露美腿"], "url": ["http://ent.qq.com/a/20150605/031371.htm"], "pdate": ["2015-06-05 12:59:30"], "image": ["http://img1.gtimg.com/ent/pics/hv1/38/5/1855/120622688_small.jpg"], "content": ["毛晓彤潮流街拍孙坚给“患者”治疗情感疾病腾讯娱乐讯正当“红绿配”席卷全球之际，即将暑期公映的青春励志爱情喜剧电影《我是奋青》也曝光了该片“鲜肉团”的应季小清新妆容。当红小生孙坚一...", "
"]}
{"src": ["腾讯娱乐", "
"], "title": ["《恋爱排班表》发劈腿特辑 遇渣男不如潇洒放手"], "url": ["http://ent.qq.com/a/20150605/031341.htm"], "pdate": ["2015-06-05 12:57:52"], "image": ["http://img1.gtimg.com/ent/pics/hv1/250/4/1855/120622645_small.jpg"], "content": ["《恋爱排班表》渣男脚踩两只船《恋爱排班表》渣男左右逢源腾讯娱乐讯将于6月26日上映的爱情喜剧大片《恋爱排班表》，今日发布了素人谈劈腿的催泪特辑。特辑中，受访对象无论男女，都卸下心...", "
"]}
{"src": ["腾讯娱乐", "
"], "title": ["《煎饼侠》曝袭胸版海报 袁姗姗、柳岩难逃黑手"], "url": ["http://ent.qq.com/a/20150605/030891.htm"], "pdate": ["2015-06-05 12:25:10"], "image": ["http://img1.gtimg.com/12/1279/127906/12790698_small.jpg"], "content": ["腾讯娱乐讯 由大鹏执导主演，袁姗姗、柳岩、尚格·云顿领衔的暑期档唯一爆笑喜剧《煎饼侠》今日再度重磅发布“袭胸版”人物海报，以百老汇风格的化妆镜为背景，通过三种不同的主题颜色暗示了...", "
"]}
{"src": ["腾讯娱乐", "
"], "title": ["《七月半》首部中元节电影 打造新恐怖系列品牌"], "url": ["http://ent.qq.com/a/20150603/039094.htm"], "pdate": ["2015-06-03 14:11:58"], "image": ["http://img1.gtimg.com/ent/pics/hv1/65/136/1853/120526070_small.jpg"], "content": ["《七月半》打造新恐怖系列品牌腾讯娱乐讯近日，由90后新锐海归导演杜潇傲执导，余心恬、翟子陌、付曼等青年偶像演员主演的恐怖电影《七月半》已宣布于8月14日全国公映，国内首部为中元节...", "
"]}
{"src": ["腾讯娱乐", "
"], "title": ["《对风说爱你》入围电影节 李晓川杨佑宁变奶爸"], "url": ["http://ent.qq.com/a/20150603/038993.htm"], "pdate": ["2015-06-03 14:10:04"], "image": ["http://img1.gtimg.com/ent/pics/hv1/226/135/1853/120525976_small.jpg"], "content": ["《对风说爱你》李晓川杨佑宁胡宇崴“喜当爹”腾讯娱乐讯金马导演王童执导最具情怀爱情电影《对风说爱你》即将在6月19日公映，近日，电影作为唯一的华语电影首批入围上海国际电影节。而其中...", "
"]}
{"src": ["腾讯娱乐", "
"], "title": ["《异种》微电影“艳女杀手” 看电影不要叨比叨"], "url": ["http://ent.qq.com/a/20150603/037932.htm"], "pdate": ["2015-06-03 14:06:47"], "image": ["http://img1.gtimg.com/12/1277/127703/12770322_small.jpg"], "content": ["  腾讯娱乐讯 即将于6月5日暑期上映的重口味新型惊悚电影《异种》 今日发布了一款创意新颖的具有“公益”色彩的微电影。短短2分钟讲述一个电影院暗杀行动，结局却有意外惊喜，更给力的...", "
"]}
{"src": ["腾讯娱乐", "
"], "title": ["“六一档”三国鼎立 小潜艇“捍卫”国产动画片"], "url": ["http://ent.qq.com/a/20150603/037104.htm"], "pdate": ["2015-06-03 14:03:20"], "image": ["http://img1.gtimg.com/12/1277/127702/12770267_small.jpg"], "content": ["  腾讯娱乐讯 每年的六一儿童节来临之际，都是动画电影争夺市场的大好时机。今年的竞争依旧激烈无比，前有迪士尼的《明日世界》、日本的经典动画《哆啦A梦：伴我同行》来势汹汹，后有“六...", "
"]}
{"src": ["腾讯娱乐", "
"], "title": ["【午夜放映】断背山: 荡气回肠同志情"], "url": ["http://ent.qq.com/a/20150603/036016.htm"], "pdate": ["2015-06-03 13:18:11"], "image": ["http://img1.gtimg.com/ent/pics/hv1/68/128/1853/120524033_small.jpg"], "content": ["华人大导演李安一举斩获威尼斯、奥斯卡等大奖的优质影片，讲述一段可歌可泣的同志爱情故事。...", "
"]}
{"src": ["腾讯娱乐", "
"], "title": ["【主题放映】腹肌加身过夏天"], "url": ["http://ent.qq.com/a/20150603/035954.htm"], "pdate": ["2015-06-03 13:14:05"], "image": ["http://img1.gtimg.com/ent/pics/hv1/46/128/1853/120524011_small.jpg"], "content": ["《激战》剧照腾讯娱乐专稿（文/朱洋洋）本期腾讯视频主题放映网罗银幕上腹肌加身的英雄猛男，亲临各种火爆对决，点燃夏日激情。激战[粤语版]>>>点击观看高清正片擂台是拳手的荣耀之地，...", "
"]}
{"src": ["腾讯娱乐", "
"], "title": ["《对风说爱你》发再见高考海报 郭采洁重拾青春"], "url": ["http://ent.qq.com/a/20150605/030861.htm"], "pdate": ["2015-06-05 12:23:15"], "image": ["http://img1.gtimg.com/12/1279/127906/12790694_small.jpg"], "content": ["腾讯娱乐讯 继宣布改档6月26日后，电影《对风说爱你》趁高考来临之际，发布了“再见—高考”版主题海报，祝福广大考生的同时，带领观众重拾青春中美好但不完美的记忆。“恋过伤过睡过疼过...", "
"]}
{"src": ["腾讯娱乐", "
"], "title": ["《惊魂电影院》曝鬼手海报 开启另类地狱之门"], "url": ["http://ent.qq.com/a/20150605/030829.htm"], "pdate": ["2015-06-05 12:21:31"], "image": ["http://img1.gtimg.com/ent/pics/hv1/122/2/1855/120622007_small.jpg"], "content": ["《惊魂电影院》鬼手版海报腾讯娱乐讯由80后新锐藏族导演王鸣执导，姚一奇、林晓凡、蒋中炜、王晔、赵圆圆、裘恩典、于清斌、张灵儿、韩雪莲等主演的恐怖电影《惊魂电影院》将于6月19日全...", "
"]}
{"src": ["腾讯娱乐", "
"], "title": ["《汽车人总动员》发场景照 动画版速度与激情"], "url": ["http://ent.qq.com/a/20150605/030772.htm"], "pdate": ["2015-06-05 12:17:03"], "image": ["http://img1.gtimg.com/12/1279/127906/12790663_small.jpg"], "content": ["腾讯娱乐讯 由动漫导演卓建荣执导的最新国内唯一赛车题材的喜剧动画电影《汽车人总动员》即将于7月4日全国上映，该电影由蓝火焰影视公司出品，中影数字、北京基点影视公司联合发行，日前片...", "
"]}
{"src": ["腾讯娱乐", "
"], "title": ["《奥拉星》推首部大电影 抢滩暑假定档7月23日"], "url": ["http://ent.qq.com/a/20150605/030629.htm"], "pdate": ["2015-06-05 12:13:02"], "image": ["http://img1.gtimg.com/ent/pics/hv1/137/0/1855/120621512_small.jpg"], "content": ["腾讯娱乐讯3D动画大电影《奥拉星·进击圣殿》今日曝光了一支萌版预告片，展现了兰丁、太二以及雪萌等主要角色相识、相交、相守的历程。同时，这部由珠江影业、百田科技、炫动传播、上海天漫...", "
"]}
{"src": ["腾讯娱乐", "
"], "title": ["纪录片《美丽乡愁》海报曝光 6月18日南京首映"], "url": ["http://ent.qq.com/a/20150605/027074.htm"], "pdate": ["2015-06-05 11:27:27"], "image": ["http://img1.gtimg.com/12/1279/127901/12790128_small.jpg"], "content": ["腾讯娱乐讯 纪录电影《美丽乡愁》首映式暨陕西、贵州孤老救助捐赠仪式将于2015年6月18日在南京新街口国际影城举行。近日，片方正式发布了两款定版海报。唯美海报还原无尽乡愁“乡音散...", "
"]}
{"src": ["腾讯娱乐", "
"], "title": ["“大自然在说话”曝粤语短片 周迅汤唯配音"], "url": ["http://ent.qq.com/a/20150605/026994.htm"], "pdate": ["2015-06-05 11:25:20"], "image": ["http://img1.gtimg.com/12/1278/127899/12789978_small.jpg"], "content": ["腾讯娱乐讯 自4月8日以来，7部“大自然在说话”系列公益影片的中文版来到中国，以每周一部的频率相继曝光后，获得了公众的持续关注，并广受好评。近日，“大自然在说话”官方网站将陆续发...", "
"]}
{"src": ["腾讯娱乐", "
"], "title": ["《妈咪侠》热映 冯宝宝被赞拉风励志"], "url": ["http://ent.qq.com/a/20150604/056338.htm"], "pdate": ["2015-06-04 22:44:54"], "image": ["http://img1.gtimg.com/ent/pics/hv1/221/148/1854/120594311_small.jpg"], "content": ["《妈咪侠》腾讯娱乐讯励志亲情喜剧《妈咪侠》正在热映，六一节期间因电影的合家欢励志主题受到了许多家长的支持，主演冯宝宝还被网友称赞“拉风又励志”，冯宝宝的“超人妈咪”形象也受到许多...", "
"]}
{"src": ["腾讯娱乐", "
"], "title": ["《三城记》曝新剧照 缔造奥斯卡级乱世美学"], "url": ["http://ent.qq.com/a/20150604/056173.htm"], "pdate": ["2015-06-04 22:34:44"], "image": ["http://img1.gtimg.com/12/1278/127847/12784705_small.jpg"], "content": ["腾讯娱乐讯  由刘青云、汤唯、秦海璐、井柏然及黄觉主演，《岁月神偷》金牌搭档张婉婷导演、罗启锐监制的影片《三城记》今日发布“缔造三城记”幕后特辑。影片场景宏大制作精良，邀请曾获奥...", "
"]}
{"src": ["腾讯娱乐", "
"], "title": ["《捉妖记》曝巨妖来袭预告 巨型血妖扑倒胡巴"], "url": ["http://ent.qq.com/a/20150604/055614.htm"], "pdate": ["2015-06-04 22:03:30"], "image": ["http://img1.gtimg.com/12/1278/127845/12784570_small.jpg"], "content": ["腾讯娱乐讯 由许诚毅导演，白百何、井柏然领衔主演，即将于7月16日上映的奇幻爆笑巨制《捉妖记》继之前连发三支“有妖气”预告后，今日又发布了一款“巨妖来袭”版预告和一组白百何、汤唯...", "
"]}
{"src": ["腾讯娱乐", "
"], "title": ["公益电影《天边的孩子》成都见面 传递正能量"], "url": ["http://ent.qq.com/a/20150604/041177.htm"], "pdate": ["2015-06-04 15:51:40"], "image": ["http://img1.gtimg.com/ent/pics/hv1/168/101/1854/120582273_small.jpg"], "content": ["腾讯娱乐讯5月31日，电影《天边的孩子》剧组主创来到成都宣传公益电影《天边的孩子》、心情愉悦的杜海涛牵着小主演小花的手（穆梦娇饰）一出场便热情的跟四川媒体朋友打招呼，大赞成都小吃...", "
"]}
{"src": ["腾讯娱乐", "
"], "title": ["黎一墨随《横冲直撞》宣传：做赵薇般的电影人"], "url": ["http://ent.qq.com/a/20150604/041102.htm"], "pdate": ["2015-06-04 15:49:51"], "image": ["http://img1.gtimg.com/12/1278/127822/12782288_small.jpg"], "content": ["腾讯娱乐讯 昨日，电影《横冲直撞好莱坞》主创华裔导演林诣彬、中国内地演员赵薇、黄晓明现身洛杉矶TCL中国大剧院，在“星光大道”上留下属于自己的代表着电影人无上荣耀的手印。同时该部...", "
"]}
{"src": ["腾讯娱乐", "
"], "title": ["《我是谁2015》发公路版海报 巅峰对决一触即发"], "url": ["http://ent.qq.com/a/20150603/032189.htm"], "pdate": ["2015-06-03 12:09:20"], "image": ["http://img1.gtimg.com/ent/pics/hv1/1/123/1853/120522691_small.jpg"], "content": ["《我是谁2015》公路版海报腾讯娱乐讯由成龙监制的今夏最燃动作大戏《我是谁2015》即将于6月12日燃情上映。近日，影片曝光了一款公路版海报，这款海报延续了之前几款海报的热血大气...", "
"]}
{"src": ["腾讯娱乐", "
"], "title": ["电影纪录片《千年莫高》 张智皓饰演霸气单于"], "url": ["http://ent.qq.com/a/20150603/031752.htm"], "pdate": ["2015-06-03 12:08:14"], "image": ["http://img1.gtimg.com/ent/pics/hv1/197/122/1853/120522632_small.jpg"], "content": ["张智皓腾讯娱乐讯曾在《白发魔女之明月天国》、《忠烈杨家将》、《花木兰》(赵薇版动画版)、《大魔术师》、《龙门飞甲》、《画皮2》等大电影，《战神韩信》、《楚留香新传》等优秀电视剧中...", "
"]}
{"src": ["腾讯娱乐", "
"], "title": ["《济公》横店开机 郑元畅出演史上最帅“济公”"], "url": ["http://ent.qq.com/a/20150603/030890.htm"], "pdate": ["2015-06-03 12:06:38"], "image": ["http://img1.gtimg.com/ent/pics/hv1/120/122/1853/120522555_small.jpg"], "content": ["《济公》横店开机腾讯娱乐讯近日由杭州南广影视投资，著名导演刘嘉靖执导的传奇古装喜剧电影《济公》在横店影视城浪漫开机。该剧由台湾偶像演员郑元畅担当男一号出演济公，童菲、安七炫、杜海...", "
"]}
{"src": ["腾讯娱乐", "
"], "title": ["《北京时间》陈乔恩变身工装女神 再现浪漫青春"], "url": ["http://ent.qq.com/a/20150603/030150.htm"], "pdate": ["2015-06-03 12:04:54"], "image": ["http://img1.gtimg.com/12/1276/127696/12769668_small.jpg"], "content": ["腾讯娱乐讯 梳着马尾辫、穿着工装服，电影《北京时间》中，不施粉黛的陈乔恩犹如少女般轻装简行，臂腕中时常搂着的一大摞书本凸显着她工程师的身份，低眉敛目中透着浓浓的书卷味儿。站在清一...", "
"]}
{"src": ["腾讯娱乐", "
"], "title": ["《道士下山》再曝预告 张震谈郭富城：他爱耍宝"], "url": ["http://ent.qq.com/a/20150603/029065.htm"], "pdate": ["2015-06-03 11:32:40"], "image": ["http://img1.gtimg.com/ent/pics/hv1/63/112/1853/120519948_small.jpg"], "content": ["小道士萌化张震张震海报腾讯娱乐讯（文/付超图/薛建宇视频/阿洋）6月2日，由陈凯歌执导，王宝强、郭富城、张震、林志玲等人主演的《道士下山》在京举办发布会。发布会上，片方公布了最新...", "
"]}
{"src": ["腾讯娱乐", "
"], "title": ["《摇滚英雄》曝明星特辑 秦昊：摇滚是一种态度"], "url": ["http://ent.qq.com/a/20150603/022897.htm"], "pdate": ["2015-06-03 10:25:16"], "image": ["http://img1.gtimg.com/ent/pics/hv1/14/88/1853/120513779_small.jpg"], "content": ["释放青春激情来袭定档海报腾讯娱乐讯即将于6月19日上映的《摇滚英雄》发布了“摇滚是什么？”制作特辑，影片众主创伊能静、秦昊、李梦、刘雅瑟，以及当红摇滚乐队逃跑计划、好妹妹、旅行团...", "
"]}
{"src": ["腾讯娱乐", "
"], "title": ["《宅女侦探桂香》高能海报 周渝民王珞丹互动"], "url": ["http://ent.qq.com/a/20150605/026343.htm"], "pdate": ["2015-06-05 11:15:03"], "image": ["http://img1.gtimg.com/12/1278/127898/12789878_small.jpg"], "content": ["腾讯娱乐讯 由彭顺执导，王珞丹、周渝民、任达华、天心、鲍起静领衔主演的小妞侦探电影《宅女侦探桂香》即将在7月24日全国公映。影片于今日曝光一组周渝民“高能”版海报，周渝民身穿黑色...", "
"]}
{"src": ["中国新闻网", "
"], "title": ["“新华字典”也能改编影视剧？国内IP热靠噱头"], "url": ["http://ent.qq.com/a/20150605/021692.htm"], "pdate": ["2015-06-05 10:26:00"], "image": ["http://img1.gtimg.com/ent/pics/hv1/16/226/1854/120613996_small.jpg"], "content": ["新华字典也被当作了影视IP文汇报6月2日报道（文/首席记者王彦）IP（知识产权）热在影视圈持续升温，几乎每天都有所谓IP电影开拍或上映。最新的消息是，“新华字典”和“俄罗斯方块”...", "
"]}
{"src": ["腾讯娱乐", "
"], "title": ["《搏击迷城》领跑暑期档 陈伟霆分裂搏击众女神"], "url": ["http://ent.qq.com/a/20150605/021357.htm"], "pdate": ["2015-06-05 10:20:09"], "image": ["http://img1.gtimg.com/12/1278/127885/12788506_small.jpg"], "content": ["腾讯娱乐讯 由内蒙古电影集团有限责任公司、金港国际影业有限公司、天极数码制作有限公司、香港电影发展基金联合出品，陈丽英导演，陈伟霆、赵柯、李菲儿、斯琴高娃、郑佩佩、刘兆铭等领衔主...", "
"]}
{"src": ["腾讯娱乐", "
"], "title": ["《无法证明》台词打动买红妹 不畏争议演女文青"], "url": ["http://ent.qq.com/a/20150605/020890.htm"], "pdate": ["2015-06-05 10:13:27"], "image": ["http://img1.gtimg.com/ent/pics/hv1/196/220/1854/120612646_small.jpg"], "content": ["儿子刘笑无法理解母亲的爱情买红妹儿子独自祭拜被母亲气死的父亲买红妹婚内约会情人朱永棠默默等候了20年爱情的买红妹腾讯娱乐讯由北京飞天魅影文化传播有限公司出品，诺贝尔文学奖获得者莫...", "
"]}
{"src": ["腾讯娱乐", "
"], "title": ["《摇滚英雄》热血来袭 “青春裸爱”诉情感"], "url": ["http://ent.qq.com/a/20150605/019983.htm"], "pdate": ["2015-06-05 10:05:52"], "image": ["http://img1.gtimg.com/ent/pics/hv1/71/218/1854/120612011_small.jpg"], "content": ["剧照剧照剧照剧照腾讯娱乐讯青春是什么，似乎只有在经历梦想破裂、爱人背叛等事件后，方才恍然大悟。在青春片兴起的时间段，越来越多的同类型题材如雨后春笋般袭来。如今，当由新锐导演谭华执...", "
"]}
{"src": ["腾讯娱乐", "
"], "title": ["许韶洋遭背叛 变“犀利哥” 《简单爱》遇情劫"], "url": ["http://ent.qq.com/a/20150605/018990.htm"], "pdate": ["2015-06-05 10:02:46"], "image": ["http://img1.gtimg.com/ent/pics/hv1/112/214/1854/120611032_small.jpg"], "content": ["许绍洋与前女友凡子（许韶洋饰）、萧晓凤（张琳饰）腾讯娱乐讯浪漫爱情喜剧《简单爱》已正式定档7月3日上映，许韶洋为爱受情伤，上演了一段被兄弟背叛，被女人劈腿的狗血戏码。据悉，许韶洋...", "
"]}
{"src": ["腾讯娱乐", "
"], "title": ["电影《小时代4》离别在即 顾准任言恺感恩观众"], "url": ["http://ent.qq.com/a/20150604/040192.htm"], "pdate": ["2015-06-04 15:30:13"], "image": ["http://img1.gtimg.com/ent/pics/hv1/123/96/1854/120580953_small.jpg"], "content": ["《小时代4》冰封海报--任言恺饰演顾准任言恺《小时代4》剧照任言恺饰演顾准腾讯娱乐讯电影《小时代4》即将上映，轰轰烈烈的“小时代毕业礼”也在全国各地举行。从电影《小时代3》中加盟...", "
"]}
{"src": ["腾讯娱乐", "
"], "title": ["王晓龙亮相《顺风车》首映 小人物传递正能量"], "url": ["http://ent.qq.com/a/20150604/039795.htm"], "pdate": ["2015-06-04 15:21:27"], "image": ["http://img1.gtimg.com/ent/pics/hv1/45/94/1854/120580365_small.jpg"], "content": ["王晓龙亮相《顺风车》首映礼腾讯娱乐讯近日，由李广德、岳晓琳导演，王永、张会中、王晓龙联合主演的国内首部关注交通问题的电影《顺风车》在金源星美国际影城举行了电影首映礼，演员王晓龙与...", "
"]}
{"src": ["腾讯娱乐", "
"], "title": ["《碟中谍5》预告独家首发 阿汤再接不可能任务"], "url": ["http://ent.qq.com/a/20150604/031616.htm"], "pdate": ["2015-06-04 15:01:01"], "image": ["http://img1.gtimg.com/12/1278/127805/12780588_small.jpg"], "content": ["《碟中谍5》海报 新预告下午腾讯视频独家首发...", "
"]}
{"src": ["腾讯娱乐", "
"], "title": ["深影视联携佳作亮相文博会 助力行业长足发展"], "url": ["http://ent.qq.com/a/20150604/036605.htm"], "pdate": ["2015-06-04 14:13:04"], "image": ["http://img1.gtimg.com/12/1278/127809/12780968_small.jpg"], "content": ["腾讯娱乐讯 中国（深圳）国际文化产业博览交易会（简称”文博会”）是中国唯一一个国家级、国际化、综合性的文化产业博览交易会，堪称全民的文化盛宴。5月14-18日，第十一届”文博会“...", "
"]}
{"src": ["腾讯